{
  "autentificacion": [
    {
      "id": 1,
      "dni": "50501313Y",
      "pin": "AK3T",
      "date": "7/3/2023, 08:40:45"
    },
    {
      "id": 2,
      "dni": "50501313Y",
      "pin": "ASM1",
      "date": "13/2/2023, 08:40:35"
    },
    {
      "id": 3,
      "dni": "71472281B",
      "pin": "7YZR",
      "date": "7/3/2023, 08:40:45"
    },
    {
      "id": 4,
      "dni": "71042966Z",
      "pin": "L2TN",
      "date": "7/3/2023, 08:40:45"
    },
    {
      "dni": "48122234R",
      "pin": "4XQC",
      "date": "7/3/2023,9:25:22",
      "id": 5
    },
    {
      "dni": "47563214T",
      "pin": "4XQC",
      "date": "7/3/2023,10:09:12",
      "id": 6
    },
    {
      "dni": "48122234R",
      "pin": "4XQC",
      "date": "7/3/2023, 10:39:02",
      "id": 7
    },
    {
      "dni": "12345678R",
      "pin": "4XQC",
      "date": "7/3/2023, 10:42:34",
      "id": 8
    },
    {
      "dni": "12345678R",
      "pin": "4XQC",
      "date": "7/3/2023, 10:43:53",
      "id": 9
    },
    {
      "dni": "12345678R",
      "pin": "4XQC",
      "date": "7/3/2023, 10:44:59",
      "id": 10
    },
    {
      "dni": "12345679R",
      "pin": "SYV6",
      "date": "7/3/2023, 10:45:23",
      "id": 11
    },
    {
      "dni": "48122234R",
      "pin": "DB1R",
      "date": "7/3/2023, 10:51:47",
      "id": 12
    },
    {
      "dni": "98745612T",
      "pin": "8ZIP",
      "date": "7/3/2023, 11:04:54",
      "id": 13
    },
    {
      "dni": "47563214T",
      "pin": "8GDB",
      "date": "7/3/2023, 11:07:25",
      "id": 14
    }
  ]
}